{
  "$schema": "../../manifest.schema.json",
  "name": "roadmap",
  "families": ["state-markers"],
  "function": "progression",
  "bucket": "chart",
  "form": "matrix",
  "substance": "structure",
  "tags": ["planning", "swimlane", "milestones", "agile"],
  "description": "Phased multi-workstream grid — phases across the top, workstreams down the side.",
  "purpose": "Use to show what ships in each phase across multiple parallel workstreams. Cells render as state-token discs (pass/warn/fail/skip).",
  "variants": [
    "horizons",
    "status",
    "swimlane",
    "milestones"
  ],
  "slots": {
    "title": {
      "selector": "h2",
      "required": true,
      "description": "Slide heading naming the plan."
    },
    "rows": {
      "selector": "table",
      "required": true,
      "description": "A markdown table. The header row lists the phases (each may carry an inline-code date pill, e.g. `Q2 2026`); the first column is the workstream name; each cell leads with a state marker [x]/[-]/[ ]/[/] then the deliverable."
    }
  },
  "skeleton": "<!-- _class: roadmap -->\n\n`H2 2026 · Plan`\n\n## What ships in each phase, by workstream.\n\n| Workstream | Foundation `Q2 2026` | Hardening `Q3 2026` | Scale `Q4 2026` |\n| --- | --- | --- | --- |\n| First workstream | [x] Shipped item | [-] In-flight item | [ ] Planned item |\n| Second workstream | [x] Shipped item | [/] Out-of-scope item | [ ] Planned item |\n\nState markers `[x]/[-]/[ ]/[/]` are universal: ✓ shipped, – in flight, ○ planned, ╱ out of scope.\n",
  "anatomyBlock": "roadmap",
  "sample": "<!-- _class: roadmap -->\n\n`H2 2026 · Rollout plan`\n\n## What ships in each phase, assuming the phases survive the next planning offsite.\n\n| Workstream | Foundation `Q2 2026`   | Hardening `Q3 2026`      | Scale `Q4 2026`         |\n| ---------- | ---------------------- | ------------------------ | ----------------------- |\n| Framework  | [x] Signal taxonomy    | [-] Scoring model v2     | [ ] Per-team weighting  |\n| Adoption   | [x] Pilot onboarding   | [-] Weekly signal review | [ ] Org-wide rollout    |\n| Governance | [x] Decision log       | [x] Calibration cadence  | [ ] Board reporting     |\n| Tooling    | [x] Intake form        | [/] Dashboards           | [ ] Self-serve exports  |\n",
  "whenToUse": [
    {
      "title": "Phased delivery across workstreams",
      "body": "When the question is what each team ships in each phase. Workstreams down the side, phases across the top, deliverables in the cells — the whole plan reads in one glance."
    },
    {
      "title": "State markers are the second channel",
      "body": "Every cell can lead with `[x]` shipped, `[-]` in flight, `[ ]` planned, or `[/]` out of scope. The audience sees both 'what' and 'how it's going' without a separate status slide."
    },
    {
      "title": "Phase headers carry meta pills",
      "body": "Append `` `Q2 2026` `` to a phase header and the renderer anchors a meta pill on the right of the column. Use it for date, owner, or status tags that frame the phase."
    }
  ],
  "antiPatterns": [
    {
      "title": "One workstream",
      "body": "A single row of phases is a `timeline` or `list-steps`, not a roadmap. Roadmap earns its grid only when at least two workstreams move in parallel."
    },
    {
      "title": "No state markers",
      "body": "A grid of bare deliverables loses half its value. Add `[x]`/`[-]`/`[ ]`/`[/]` so the audience reads progress alongside scope."
    },
    {
      "title": "Past five workstreams",
      "body": "More than five rows compresses cell text and the lane stripes lose their categorical read. Group adjacent workstreams or split by phase."
    }
  ],
  "related": [
    {
      "name": "gantt",
      "when": "continuous task bars across a date axis rather than discrete phase cells"
    },
    {
      "name": "kanban",
      "when": "current state by stage rather than phased schedule"
    },
    {
      "name": "list-steps",
      "when": "single workstream sequence without parallel lanes"
    },
    {
      "name": "verdict-grid",
      "when": "options scored against shared criteria, not phased delivery"
    },
    {
      "name": "checklist",
      "when": "single list with state markers, no workstream dimension"
    }
  ],
  "variantDocs": {
    "horizons": {
      "label": "Horizons — three-horizon planning framing",
      "caption": "Tints the phase columns as Horizon 1 / 2 / 3 (now / next / later) per the McKinsey three-horizons framing. Use when the planning frame is strategic-horizon-aware rather than fiscal-quarter-aware.",
      "sample": "<!-- _class: roadmap horizons -->\n\n`Three-horizon planning`\n\n## Where the framework invests across horizons — Horizon 3 has lived there since 2024.\n\n| Workstream    | Horizon 1 `Now`          | Horizon 2 `Next`         | Horizon 3 `Later`         |\n| ------------- | ------------------------ | ------------------------ | ------------------------- |\n| Signal Intake | [x] Connector v1     | [-] Multi-source dedupe    | [ ] Anomaly auto-routing |\n| Scoring       | [x] Equal weights      | [-] Per-team calibration   | [ ] Per-decision profiles |\n| Decision Log  | [x] Append-only schema   | [x] Outcome auto-pairing | [ ] Auditor export        |\n| Adoption      | [x] One pilot team       | [/] Second team          | [ ] Org-wide enablement   |\n\nHorizons frame the read: H1 is core business, H2 is emerging, H3 is the option set.\n"
    },
    "status": {
      "label": "Status — heavy state treatment",
      "caption": "Promotes the state markers ([x]/[-]/[ ]/[/]) to the dominant read: tinted cell grounds, an uppercase state eyebrow, and a corner state disc. Use for the standing delivery-status review.",
      "sample": "<!-- _class: roadmap status -->\n\n`Layout · roadmap status`\n\n## Delivery status by workstream, as of the most flattering snapshot.\n\n| Workstream    | Foundation `Q2 2026` | Hardening `Q3 2026`      | Scale `Q4 2026`           |\n| ------------- | -------------------- | ------------------------ | ------------------------- |\n| Signal Intake | [x] Connector v1 | [-] Multi-source dedupe    | [ ] Anomaly auto-routing |\n| Scoring       | [x] Equal weights    | [-] Per-team calibration | [ ] Per-decision profiles |\n| Decision Log  | [x] Append schema    | [x] Outcome pairing      | [ ] Auditor export        |\n| Adoption      | [x] One pilot team   | [/] Second team          | [ ] Org-wide enablement   |\n\nState markers `[x]/[-]/[ ]/[/]` are universal: ✓ shipped, – in flight, ○ planned, ╱ out of scope.\n"
    },
    "swimlane": {
      "label": "Swimlane — horizontal tracks",
      "caption": "Renders each workstream as a horizontal track across the phase columns, so a reader scans one team's whole journey left-to-right before moving to the next.",
      "sample": "<!-- _class: roadmap swimlane -->\n\n`Layout · roadmap swimlane`\n\n## Each team's track across the year, momentum implied by the arrows.\n\n| Workstream    | Foundation `Q2 2026` | Hardening `Q3 2026`    | Scale `Q4 2026`           |\n| ------------- | -------------------- | ---------------------- | ------------------------- |\n| Signal Intake | Connector v1     | Multi-source dedupe        | Anomaly auto-routing  |\n| Scoring       | Equal weights        | Per-team calibration   | Per-decision profiles    |\n| Decision Log  | Append schema        | Outcome pairing        | Auditor export            |\n| Adoption      | One pilot team       | Second team            | Org-wide enablement       |\n"
    },
    "milestones": {
      "label": "Milestones — calendar-aware",
      "caption": "Treats the phase headers as dated milestones, carrying their date pill as a subtitle. Use when the cadence of the dates is part of the story, not just the sequence.",
      "sample": "<!-- _class: roadmap milestones -->\n\n`Layout · roadmap milestones`\n\n## The dated path to GA, dates subject to the usual revision.\n\n| Workstream    | Beta `Q2 2026`       | RC `Q3 2026`           | GA `Q4 2026`              |\n| ------------- | -------------------- | ---------------------- | ------------------------- |\n| Signal Intake | Connector v1     | Multi-source dedupe        | Anomaly auto-routing  |\n| Scoring       | Equal weights        | Per-team calibration   | Per-decision profiles    |\n| Decision Log  | Append schema        | Outcome pairing        | Auditor export            |\n"
    }
  },
  "showcase": { "featured": true }
}
